{"other":{"id":13163,"type":"Other","title":"Other notice to Google, Inc.","date_sent":"2011-07-01T04:00:00Z","date_received":"2011-07-01T04:00:00Z","topics":["Uncategorized"],"sender_name":"Linda Smit","principal_name":null,"recipient_name":"Google, Inc.","works":[{"complaint":"I searched this:  \"Bible clip art figures, women at\nthe  \ntomb, coloring pages\" and got this address with images:","original_work_urls":[],"problematic_urls":[{"url":"http://cegadaba.blogspot.com/2011/06/religious-easter-clipart.html"}]}],"tags":[],"jurisdictions":[],"action_taken":"Yes","language":null,"explanation":null}}