{"dmca":{"id":45130,"type":"Dmca","title":"A Breath of Copyright Complaint Against Cherubs","body":"It has come to our attention that your client is using copyrighted content on her website www.cdhsupport.org, without authorization.  \r\n\r\nOn the website, the page ","date_sent":"2007-10-01T04:00:00Z","date_received":"2007-10-01T04:00:00Z","topics":["Copyright","Copyright and Fair Use"],"sender_name":null,"principal_name":"Breath of Hope, Inc.","recipient_name":"Cherubs","works":[{"description":"Unknown work","infringing_urls":[],"copyrighted_urls":[]}],"tags":[],"jurisdictions":[],"action_taken":"Yes","language":null}}