{"dmca":{"id":14114,"type":"Dmca","title":"Adult Video DMCA (Copyright) Complaint to Google","body":null,"date_sent":"2012-07-30T04:00:00Z","date_received":"2012-07-30T04:00:00Z","topics":["Copyright","DMCA Safe Harbor"],"sender_name":"Degban Ltd","principal_name":"BangBros.com Inc.","recipient_name":"Google, Inc.","works":[{"description":"Video and Image series produced by BangBros.com Inc. under brand title Brown Bunnies","infringing_urls":[{"url":"http://www.porn-w.org/viewtopic.php?p=9100368"},{"url":"http://www.final4ever.com/7998828-post1.html"},{"url":"http://www.porn-w.org/viewtopic.php?p=9175160"},{"url":"http://www.final4ever.com/7996766-post1.html"},{"url":"http://www.porn-w.org/viewtopic.php?p=9259704"},{"url":"http://www.porn-w.org/viewtopic.php?p=9133790"},{"url":"http://www.porn-w.org/viewtopic.php?p=8253325"},{"url":"http://www.porn-w.org/viewtopic.php?p=9201531"},{"url":"http://www.porn-w.org/viewtopic.php?p=9094044"},{"url":"http://www.porn-w.org/viewtopic.php?p=9113429"},{"url":"http://www.porn-w.org/viewtopic.php?p=9124813"},{"url":"http://www.porn-w.org/viewtopic.php?p=9133680"},{"url":"http://www.final4ever.com/7985174-post1.html"},{"url":"http://www.porn-w.org/viewtopic.php?p=9133922"},{"url":"http://www.porn-w.org/viewtopic.php?p=9201394"},{"url":"http://www.porn-w.org/viewtopic.php?p=9149637"},{"url":"http://www.porn-w.org/viewtopic.php?p=9291098"},{"url":"http://www.final4ever.com/8073915-post1.html"},{"url":"http://www.porn-w.org/viewtopic.php?p=9175217"},{"url":"http://www.final4ever.com/7995743-post1.html"},{"url":"http://www.porn-w.org/viewtopic.php?p=9027453"},{"url":"http://www.final4ever.com/7982740-post1.html"},{"url":"http://www.porn-w.org/viewtopic.php?p=9174250"},{"url":"http://www.porn-w.org/viewtopic.php?p=9201344"},{"url":"http://www.final4ever.com/7984923-post1.html"},{"url":"http://www.porn-w.org/viewtopic.php?p=9133574"},{"url":"http://www.porn-w.org/viewtopic.php?p=9269458"},{"url":"http://www.porn-w.org/viewtopic.php?p=9300244"},{"url":"http://ifaqu.net/straight/46-amy-shores-skinny-with-a-big-butt-brownbunniescom2012hd720p.html"},{"url":"http://www.porn-w.org/viewtopic.php?p=9466798"},{"url":"http://www.porn-w.org/viewtopic.php?p=9133460"},{"url":"http://www.sharaget.com/vn3ge9Un6uZS/skinny-with-a-big-butt720p-mp4.html"},{"url":"http://www.porn-w.org/viewtopic.php?p=9125176"},{"url":"http://www.porn-w.org/viewtopic.php?p=9201466"},{"url":"http://www.final4ever.com/7996386-post1.html"},{"url":"http://www.porn-w.org/viewtopic.php?p=9201290"},{"url":"http://www.sharaget.com/vn3ge9Un6tZU/skinny-with-a-big-butt720p-mp4.html"},{"url":"http://www.porn-w.org/viewtopic.php?p=9587899"}],"copyrighted_urls":[{"url":"http://www.brownbunnies.com"},{"url":"http://member.brownbunnies.com"}]}],"tags":[],"jurisdictions":[],"action_taken":"Yes","language":null}}