{"dmca":{"id":18661,"type":"Dmca","title":"Music DMCA (Copyright) Complaint to Google","body":null,"date_sent":"2012-07-30T04:00:00Z","date_received":"2012-07-30T04:00:00Z","topics":["Copyright","DMCA Safe Harbor"],"sender_name":"Murat Yashin","principal_name":"Murat Yashin","recipient_name":"Google, Inc.","works":[{"description":"Original content of Raki can be viewed at the URL below.","infringing_urls":[{"url":"http://www.raki.net/"}],"copyrighted_urls":[{"url":"http://www.raki.com"}]}],"tags":[],"jurisdictions":[],"action_taken":"Yes","language":null}}