{"dmca":{"id":39203,"type":"Dmca","title":"DMCA (Copyright) Complaint to Google","body":null,"date_sent":"2012-01-19T05:00:00Z","date_received":"2012-01-19T05:00:00Z","topics":["Copyright","DMCA Safe Harbor"],"sender_name":"SideEffectshub.com","principal_name":"SideEffectshub.com","recipient_name":"Google, Inc.","works":[{"description":"Our was copied by a competing site and posted to article directories and other various places along with a link to their site.  We've sent several of these reports and they continue to do it even though we've asked them to stop.  It's clear they intentionally doing it to harm our site and boost their own at the same time.  It appears to be working.","infringing_urls":[{"url":"http://talewins.com/bulletin/archives/7049"},{"url":"http://wikiblog.wccards.k12.mo.us/groups/nutritionwebsitefun/weblog/80105/Metformin_Side_Effects__Drug_Details_And_Resources.html"}],"copyrighted_urls":[{"url":"http://sideeffectshub.com/metformin-side-effects/"}]}],"tags":[],"jurisdictions":[],"action_taken":"Yes","language":null}}