{"dmca":{"id":15604,"type":"Dmca","title":"KEF, via Net Enforcers, complains of images in Froogle","body":"I, the undersigned, CERTIFY UNDER PENALTY OF PERJURY that I am an agent authorized to act on behalf of the owner of certain intellectual property rights, said owner being named [  KEF ] (\"IP Owner\"). I have a good faith belief that the listings or materials listed below are not authorized by the above IP Owner, its agent, or the law and therefore infringe the IP Owner's rights according to state, federal, or United States law. Please act expeditiously to remove or disable access to the material or items claimed to be infringing.\r\n \r\n\r\nIdentity of advertisement(s) at issue/Images owned by [ KEF ] / :\r\nBrand-Electronics\r\nhttp://froogle.google.com/froogle_image?q=http://www.brand-electronics.com/img/products/icon/37239.jpg&size=2&dhm=78e55ab5&hl=en          (iQ6c)\r\nhttp://froogle.google.com/froogle_image?q=http://www.brand-electronics.com/img/products/icon/37238.jpg&size=2&dhm=114eb87a&hl=en          (iQ2c)\r\nhttp://froogle.google.com/froogle_image?q=http://www.brand-electronics.com/img/products/icon/37257.jpg&size=2&dhm=1e478ab6&hl=en          (Reference 206ds)\r\nhttp://froogle.google.com/froogle_image?q=http://www.brand-electronics.com/img/products/icon/37245.jpe&size=2&dhm=4079b461&hl=en          (Reference 203)\r\nhttp://froogle.google.com/froogle_image?q=http://www.brand-electronics.com/img/products/icon/37242.jpg&size=2&dhm=2281d140&hl=en          (Reference 204c)\r\nhttp://froogle.google.com/froogle_image?q=http://www.brand-electronics.com/img/products/icon/37248.jpg&size=2&dhm=c36dfd3d&hl=en           (KIT 100)\r\nhttp://froogle.google.com/froogle_image?q=http://www.brand-electronics.com/img/products/icon/38710.jpg&size=2&dhm=4aabd1&hl=en             (Ci 130.2qr)\r\nhttp://froogle.google.com/froogle_image?q=http://www.brand-electronics.com/img/products/icon/37241.jpg&size=2&dhm=92a6a615&hl=en          (Reference 202c)\r\nhttp://froogle.google.com/froogle_image?q=http://www.brand-electronics.com/img/products/icon/37246.jpg&size=2&dhm=17936315&hl=en          (Reference 205)\r\nBest Buy (KIT 100 Speakers)\r\nhttp://froogle.google.com/froogle_image?q=http://images.bestbuy.com/BestBuy_US/images/products/6759/6759705_sc.jpg&size=2&dhm=260a8567&hl=en  \r\nReference Audio Video (KHT 2005B)\r\nhttp://froogle.google.com/froogle_image?q=http://us.st1.yimg.com/us.st11.yimg.com/us.st.yimg.com/I/rav_1912_5026176&size=2&dhm=944eccf6&hl=en  \r\n \r\nI swear, under penalty of perjury, that the information in the notification is accurate and that, for each image identified above, I either own the copyright or am authorized to act on behalf of the owner of an exclusive right that is allegedly infringed.\r\n \r\n\r\nPrinted Name: [ [private] ]\r\nTitle & Company: [Enforcement Team, Net Enforcers, Inc.]\r\nStreet Address: [[private]]\r\nCity and State: [Gainesville, FL]\r\nZip: [32601]\r\nEmail [[private]@netenforcers.com]\r\nFax: [[private]]\r\nDate: [ 9/25/2006]\r\n \r\n\r\nTruthfully,\r\n/S/:  [private]\r\n","date_sent":"2006-09-25T04:00:00Z","date_received":"2006-09-25T04:00:00Z","topics":["Copyright","DMCA Safe Harbor"],"sender_name":"Net Enforcers, Inc.","principal_name":"KEF","recipient_name":"Google, Inc. [Froogle]","works":[{"description":"Unknown work","infringing_urls":[],"copyrighted_urls":[]}],"tags":[],"jurisdictions":[],"action_taken":"Yes","language":null}}