{"other":{"id":52053,"type":"Other","title":"Other notice to Google, Inc.","date_sent":"2012-09-26T04:00:00Z","date_received":"2012-09-26T04:00:00Z","topics":["Uncategorized"],"sender_name":"Fabio Andr\u00e9s Rodr\u00edguez V\u00e1squez","principal_name":"www.metalworks.co","recipient_name":"Google, Inc.","works":[{"complaint":"Este usuario est\u00e1 difamando nuestra marca haciendo  \nreclamo de una marca que nunca ha confirmado sea legalmente suya.  \nAdicionalmente y como ya fue notificado, est\u00e1 cometiendo violaci\u00f3n de  \nderechos de propiedad intelectual al copiar nuestro contenido y no dar  \nning\u00fan tipo de cr\u00e9dito o referenciarnos com fuente original\n\nDe acuerdo con las disposiciones vigentes sobre propiedad intelectual  \n(art\u00edculos 31 de la ley 23 de 1982 y 22 de la Decisi\u00f3n 351 de 1993 de la  \n\nComisi\u00f3n del acuerdo de Cartagena), podr\u00e1n citarse fragmentos de las obras\n \nque contiene esta p\u00e1gina, caso en el cual deber\u00e1 indicarse la fuente y  \nnombre del autor de la obra respectiva, siempre y cuando tales citas se  \nhagan conforme a los usos honrados y en una medida justificada por el fin \n\nque se persiga, de tal manera que con ello no se efect\u00fae una reproducci\u00f3n \n\nno autorizada de la obra citada.\n\nToda utilizaci\u00f3n de esta p\u00e1gina o de su contenido, diferente a la  \npermitida, o con fines comerciales o lucrativos, o que atenten de manera  \n\ndirecta contra el buen nombre o la posici\u00f3n en el mercado de  \nwww.MetalWorks.co requerir\u00e1 de la previa y expresa autorizaci\u00f3n de  \nwww.MetalWorks.co, seg\u00fan el caso, so pena de constituir violaci\u00f3n a las  \nnormas de derechos de autor.","original_work_urls":[],"problematic_urls":[{"url":"https://plus.google.com/u/0/100399811304988072916/posts/Nd6uDCSeqVH"}]}],"tags":[],"jurisdictions":[],"action_taken":"Yes","language":null,"explanation":null}}