{"dmca":{"id":40966,"type":"Dmca","title":"DMCA (Copyright) Complaint to Google","body":null,"date_sent":"2012-06-07T04:00:00Z","date_received":"2012-06-07T04:00:00Z","topics":["Copyright","DMCA Safe Harbor"],"sender_name":"ISC Technologies","principal_name":"Webmaster - IndiaStudyChannel","recipient_name":"Google, Inc.","works":[{"description":"Significant portion of our article is copied. For example as follow;\r\n\r\nhare Market is a place where everyone wants to invest their money in order to taste the Profits. But it purely depends on the fundamentals...\r\n\r\nThere are various sectors in the share market. Some of the known sectors are Oil, Reality meaning Real Estate...\r\n\r\nAs we saw above there are lot of sectors available in front of the investors. But which sector one should choose that will give good returns in short term and long term investments.","infringing_urls":[{"url":"http://www.goodinfohome.com/Art/785283/226/Things-to-know-About-the-Indian-Equity-Market.html"}],"copyrighted_urls":[{"url":"http://www.indiastudychannel.com/resources/49031-How-To-Invest-In-Share-Market.aspx"}]}],"tags":[],"jurisdictions":[],"action_taken":"Yes","language":null}}