{"dmca":{"id":4029,"type":"Dmca","title":"DMCA (Copyright) Complaint to Google","body":null,"date_sent":"2012-01-16T05:00:00Z","date_received":"2012-01-16T05:00:00Z","topics":["Copyright","DMCA Safe Harbor"],"sender_name":"Run Up Game Distribution Ltd","principal_name":"Run Up Game Distribution Ltd","recipient_name":"Google, Inc. [Chromewebstoreextensionsgallery]","works":[{"description":"\u6211\u65b9\u64c1\u6709\u7684\u7248\u6b0a\u4f5c\u54c1:\n4\u4f4d\u5973\u4e3b\u89d2\u624b\u6301\u5564\u724c\u7684\u5716\u7247","infringing_urls":[{"url":"https://chrome.google.com/webstore/detail/gibhmdjffbnlgfiaabeelnhldjnmonjj/details"}],"copyrighted_urls":[]}],"tags":[],"jurisdictions":[],"action_taken":"Yes","language":null}}