{"dmca":{"id":7247,"type":"Dmca","title":"Client Complains to Graphic Designer","body":"Larry,\r\n\r\nThis is Shannon from 160over90.  Please cease and desist immediately from making any reference to doing work for 160over90 or any of its past clients.  You are contractually not permitted to use our logo or our work as anything that you did for 160over90 was work-for-hire.  Furthermore it is causing confusion in the marketplace and jeopardizing our business.  Please confirm your intent to remove our logo and reference to that work immediately as well as any logos or reference to work for any of 160over90","date_sent":"2005-07-20T04:00:00Z","date_received":"2005-07-20T04:00:00Z","topics":["Trademark","Copyright"],"sender_name":null,"principal_name":"160over90","recipient_name":null,"works":[{"description":"Unknown work","infringing_urls":[],"copyrighted_urls":[]}],"tags":[],"jurisdictions":[],"action_taken":"Yes","language":null}}