{"dmca":{"id":3070,"type":"Dmca","title":"TheNationalDebate Responds to NYT Threat","body":"Dear [Private]:\r\n\r\nThis firm represents the management of the Internet website TheNatlonalDebate.com. We write in response to yours of March 9, 2004 to [Private] of VERIO, Inc. (","date_sent":"2004-03-15T05:00:00Z","date_received":"2004-03-15T05:00:00Z","topics":["Responses","Copyright"],"sender_name":"Coleman Law Firm","principal_name":"TheNationalDebate.com","recipient_name":"The New York Times Company","works":[{"description":"Unknown work","infringing_urls":[],"copyrighted_urls":[]}],"tags":[],"jurisdictions":[],"action_taken":"Yes","language":null}}